{"backend_mysql.md":"iISPNJc_","backend_nest.md":"CYJDw7yR","backend_redis.md":"px7hedH6","base_css.md":"DW2Cgmfl","base_git.md":"DYTOk_-8","base_js.md":"BMO47fCM","base_linux.md":"Fp1HH7yX","base_network.md":"DYLctug6","frontend_angular.md":"kt3D6Ree","frontend_next.md":"Cm0tqHi4","frontend_pinia.md":"D4ju8XnQ","frontend_react-router.md":"D3d0UDYH","frontend_react.md":"B9SN6H8X","frontend_vite.md":"DFcAjDP8","frontend_vue-router.md":"omYKpGUm","frontend_vue3-pro.md":"EgetS0rK","frontend_vue3.md":"dmrLfAjN","frontend_zustand.md":"CgOuWVS-","index.md":"DpELgojC"}
